hisim/__init__.py
hisim/component.py
hisim/component_wrapper.py
hisim/dynamic_component.py
hisim/hisim_main.py
hisim/hisim_with_profiler.py
hisim/json_executor.py
hisim/json_generator.py
hisim/loadtypes.py
hisim/log.py
hisim/postprocessingoptions.py
hisim/project_code_overview_generator.py
hisim/result_path_provider.py
hisim/sim_repository.py
hisim/sim_repository_singleton.py
hisim/simulationparameters.py
hisim/simulator.py
hisim/system_setup_configuration.py
hisim/system_setup_starter.py
hisim/units.py
hisim/utils.py
hisim/building_sizer_utils/__init__.py
hisim/building_sizer_utils/interface_configs/__init__.py
hisim/building_sizer_utils/interface_configs/archetype_config.py
hisim/building_sizer_utils/interface_configs/kpi_config.py
hisim/building_sizer_utils/interface_configs/modular_household_config.py
hisim/building_sizer_utils/interface_configs/system_config.py
hisim/components/__init__.py
hisim/components/advanced_battery_bslib.py
hisim/components/advanced_ev_battery_bslib.py
hisim/components/advanced_fuel_cell.py
hisim/components/advanced_fuel_cell_controller.py
hisim/components/advanced_heat_pump_hplib.py
hisim/components/air_conditioner.py
hisim/components/building.py
hisim/components/configuration.py
hisim/components/controller_l1_building_heating.py
hisim/components/controller_l1_chp.py
hisim/components/controller_l1_electrolyzer.py
hisim/components/controller_l1_electrolyzer_h2.py
hisim/components/controller_l1_example_controller.py
hisim/components/controller_l1_fuel_cell.py
hisim/components/controller_l1_generic_ev_charge.py
hisim/components/controller_l1_generic_runtime.py
hisim/components/controller_l1_heat_old.py
hisim/components/controller_l1_heatpump.py
hisim/components/controller_l1_rsoc.py
hisim/components/controller_l2_district_energy_management_system.py
hisim/components/controller_l2_energy_management_system.py
hisim/components/controller_l2_generic_heat_clever_simple.py
hisim/components/controller_l2_generic_heat_simple.py
hisim-1.2.3.dist-info/AUTHORS.rst
hisim-1.2.3.dist-info/LICENSE
hisim-1.2.3.dist-info/METADATA
hisim-1.2.3.dist-info/WHEEL
hisim-1.2.3.dist-info/entry_points.txt
hisim-1.2.3.dist-info/top_level.txt
hisim-1.2.3.dist-info/RECORD
