Metadata-Version: 2.1
Name: hisim
Version: 1.2.3
Summary: ETHOS.HiSim is a house infrastructure simulator
Home-page: https://github.com/FZJ-IEK3-VSA/HiSim
Author: Noah Pflugradt
Author-email: n.pflugradt@fz-juelich.de
License: MIT license
Keywords: hisim
Classifier: Development Status :: 2 - Pre-Alpha
Classifier: Intended Audience :: Developers
Classifier: License :: OSI Approved :: MIT License
Classifier: Natural Language :: English
Classifier: Programming Language :: Python :: 3
Classifier: Programming Language :: Python :: 3.5
Classifier: Programming Language :: Python :: 3.6
Classifier: Programming Language :: Python :: 3.7
Classifier: Programming Language :: Python :: 3.8
Requires-Python: >=3.5
License-File: LICENSE
License-File: AUTHORS.rst
Requires-Dist: numpy
Requires-Dist: pandas
Requires-Dist: matplotlib
Requires-Dist: seaborn
Requires-Dist: reportlab
Requires-Dist: pvlib
Requires-Dist: oemof.thermal
Requires-Dist: openpyxl
Requires-Dist: pytest
Requires-Dist: sphinx
Requires-Dist: sphinx-rtd-theme
Requires-Dist: dataclasses-json
Requires-Dist: hplib==1.9
Requires-Dist: bslib==0.6
Requires-Dist: psutil
Requires-Dist: pydot
Requires-Dist: graphviz
Requires-Dist: dataclass-wizard==0.34.0
Requires-Dist: utspclient==0.1.6
Requires-Dist: pyam-iamc
Requires-Dist: html2image
Requires-Dist: control
Requires-Dist: casadi
Requires-Dist: plotly
Requires-Dist: ordered-set
Requires-Dist: typing-extensions
Requires-Dist: python-dotenv
Requires-Dist: windpowerlib
Requires-Dist: wetterdienst==0.63.0
Requires-Dist: cdsapi
Requires-Dist: xarray
Requires-Dist: pygfunction
Requires-Dist: pyloadprofilegenerator
